{"cameraMode":{"drawMode":0,"name":"Shaded","section":"Shading Mode"},"sceneLighting":true,"audioPlay":false,"sceneViewState":{"showFog":true,"showMaterialUpdate":false,"showSkybox":true,"showFlares":true,"showImageEffects":true,"showParticleSystems":true},"in2DMode":false,"pivot":{"x":26.416893005371095,"y":-4.124995231628418,"z":-1.4919319152832032},"rotation":{"x":0.10225211828947067,"y":0.4626426696777344,"z":-0.05381954833865166,"w":0.8789849877357483},"size":44.663612365722659,"orthographic":false}